bingodb/__init__.py
bingodb-0.0.1.dist-info/METADATA
bingodb-0.0.1.dist-info/WHEEL
bingodb-0.0.1.dist-info/top_level.txt
bingodb-0.0.1.dist-info/RECORD
