Metadata-Version: 2.1
Name: bingodb
Version: 0.0.1
Summary: Postgres adapter for python flask
Home-page: UNKNOWN
Author: Dheeraj Shyam P.V.S
Author-email: aquesasolutions@gmail.com
License: MIT
Keywords: adapter
Platform: UNKNOWN
Classifier: Development Status :: 5 - Production/Stable
Classifier: Intended Audience :: Education
Classifier: Operating System :: Microsoft :: Windows :: Windows 10
Classifier: License :: OSI Approved :: MIT License
Classifier: Programming Language :: Python :: 3
